[
  {"src":"../Images/Town/Tileset_1.png","collison":true},
  {"src":"../Images/Town/Tileset_2.png","collison":true},
  {"src":"../Images/Town/Tileset_3.png","collison":true},
  {"src":"../Images/Street/Tileset_15.png","collison":true},
  {"src":"../Images/Street/Tileset_5.png","collison":false},
  {"src":"../Images/Street/Tileset_6.png","collison":false},
  {"src":"../Images/Street/Tileset_15.png","collison":true},
  {"src":"../Images/Street/Tileset_15.png","collison":true},
  {"src":"../Images/Street/Tileset_15.png","collison":true},
  {"src":"../Images/Street/Tileset_15.png","collison":true},
  {"src":"../Images/Street/Tileset_15.png","collison":true},
  {"src":"../Images/Street/Tileset_15.png","collison":true},
  {"src":"../Images/Street/Tileset_15.png","collison":true},
  {"src":"../Images/Street/Tileset_15.png","collison":true},
  {"src":"../Images/Street/Tileset_5.png","collison":false},
  {"src":"../Images/Street/Tileset_6.png","collison":false},
  {"src":"../Images/Street/Tileset_15.png","collison":true},
  {"src":"../Images/Street/Tileset_15.png","collison":true},
  {"src":"../Images/Street/Tileset_15.png","collison":true},
  {"src":"../Images/Street/Tileset_15.png","collison":true},
  {"src":"../Images/Town/Tileset_15.png","collison":true},
  {"src":"../Images/Town/Tileset_16.png","collison":true},
  {"src":"../Images/Town/Tileset_17.png","collison":true},
  {"src":"../Images/Street/Tileset_15.png","collison":true},
  {"src":"../Images/Street/Tileset_5.png","collison":false},
  {"src":"../Images/Street/Tileset_6.png","collison":false},
  {"src":"../Images/Street/Tileset_15.png","collison":true},
  {"src":"../Images/Street/Tileset_15.png","collison":true},
  {"src":"../Images/Street/Tileset_15.png","collison":true},
  {"src":"../Images/Street/Tileset_15.png","collison":true},
  {"src":"../Images/Street/Tileset_15.png","collison":true},
  {"src":"../Images/Street/Tileset_15.png","collison":true},
  {"src":"../Images/Street/Tileset_15.png","collison":true},
  {"src":"../Images/Street/Tileset_15.png","collison":true},
  {"src":"../Images/Street/Tileset_5.png","collison":false},
  {"src":"../Images/Street/Tileset_6.png","collison":false},
  {"src":"../Images/Street/Tileset_15.png","collison":true},
  {"src":"../Images/Street/Tileset_15.png","collison":true},
  {"src":"../Images/Street/Tileset_15.png","collison":true},
  {"src":"../Images/Street/Tileset_15.png","collison":true},
  {"src":"../Images/Town/Tileset_29.png","collison":true},
  {"src":"../Images/Town/Tileset_30.png","collison":true},
  {"src":"../Images/Town/Tileset_31.png","collison":true},
  {"src":"../Images/Street/Tileset_15.png","collison":true},
  {"src":"../Images/Street/Tileset_57.png","collison":false},
  {"src":"../Images/Street/Tileset_57.png","collison":false},
  {"src":"../Images/Street/Tileset_53.png","collison":false},
  {"src":"../Images/Street/Tileset_53.png","collison":false},
  {"src":"../Images/Street/Tileset_53.png","collison":false},
  {"src":"../Images/Street/Tileset_53.png","collison":false},
  {"src":"../Images/Street/Tileset_53.png","collison":false},
  {"src":"../Images/Street/Tileset_53.png","collison":false},
  {"src":"../Images/Street/Tileset_53.png","collison":false},
  {"src":"../Images/Street/Tileset_53.png","collison":false},
  {"src":"../Images/Street/Tileset_57.png","collison":false},
  {"src":"../Images/Street/Tileset_57.png","collison":false},
  {"src":"../Images/Street/Tileset_15.png","collison":true},
  {"src":"../Images/Street/Tileset_15.png","collison":true},
  {"src":"../Images/Street/Tileset_15.png","collison":true},
  {"src":"../Images/Street/Tileset_15.png","collison":true},
  {"src":"../Images/Town/Tileset_71.png","collison":true},
  {"src":"../Images/Town/Tileset_44.png","collison":true},
  {"src":"../Images/Town/Tileset_73.png","collison":true},
  {"src":"../Images/Street/Tileset_15.png","collison":true},
  {"src":"../Images/Street/Tileset_57.png","collison":false},
  {"src":"../Images/Street/Tileset_57.png","collison":false},
  {"src":"../Images/Street/Tileset_66.png","collison":false},
  {"src":"../Images/Street/Tileset_66.png","collison":false},
  {"src":"../Images/Street/Tileset_66.png","collison":false},
  {"src":"../Images/Street/Tileset_66.png","collison":false},
  {"src":"../Images/Street/Tileset_66.png","collison":false},
  {"src":"../Images/Street/Tileset_66.png","collison":false},
  {"src":"../Images/Street/Tileset_66.png","collison":false},
  {"src":"../Images/Street/Tileset_66.png","collison":false},
  {"src":"../Images/Street/Tileset_57.png","collison":false},
  {"src":"../Images/Street/Tileset_57.png","collison":false},
  {"src":"../Images/Street/Tileset_15.png","collison":true},
  {"src":"../Images/Street/Tileset_15.png","collison":true},
  {"src":"../Images/Street/Tileset_15.png","collison":true},
  {"src":"../Images/Street/Tileset_15.png","collison":true},
  {"src":"../Images/Town/Tileset_71.png","collison":true},
  {"src":"../Images/Town/Tileset_114.png","collison":true},
  {"src":"../Images/Town/Tileset_73.png","collison":true},
  {"src":"../Images/Street/Tileset_15.png","collison":true},
  {"src":"../Images/Street/Tileset_5.png","collison":false},
  {"src":"../Images/Street/Tileset_6.png","collison":false},
  {"src":"../Images/Street/Tileset_15.png","collison":true},
  {"src":"../Images/Street/Tileset_15.png","collison":true},
  {"src":"../Images/Street/Tileset_15.png","collison":true},
  {"src":"../Images/Street/Tileset_15.png","collison":true},
  {"src":"../Images/Street/Tileset_15.png","collison":true},
  {"src":"../Images/Street/Tileset_15.png","collison":true},
  {"src":"../Images/Street/Tileset_15.png","collison":true},
  {"src":"../Images/Street/Tileset_15.png","collison":true},
  {"src":"../Images/Street/Tileset_5.png","collison":false},
  {"src":"../Images/Street/Tileset_6.png","collison":false},
  {"src":"../Images/Street/Tileset_15.png","collison":true},
  {"src":"../Images/Street/Tileset_15.png","collison":true},
  {"src":"../Images/Street/Tileset_15.png","collison":true},
  {"src":"../Images/Street/Tileset_15.png","collison":true},
  {"src":"../Images/Street/Tileset_15.png","collison":true},
  {"src":"../Images/Street/Tileset_15.png","collison":true},
  {"src":"../Images/Street/Tileset_15.png","collison":true},
  {"src":"../Images/Street/Tileset_15.png","collison":true},
  {"src":"../Images/Street/Tileset_5.png","collison":false},
  {"src":"../Images/Street/Tileset_6.png","collison":false},
  {"src":"../Images/Street/Tileset_15.png","collison":true},
  {"src":"../Images/Street/Tileset_15.png","collison":true},
  {"src":"../Images/Street/Tileset_15.png","collison":true},
  {"src":"../Images/Street/Tileset_15.png","collison":true},
  {"src":"../Images/Street/Tileset_15.png","collison":true},
  {"src":"../Images/Street/Tileset_15.png","collison":true},
  {"src":"../Images/Street/Tileset_15.png","collison":true},
  {"src":"../Images/Street/Tileset_15.png","collison":true},
  {"src":"../Images/Street/Tileset_5.png","collison":false},
  {"src":"../Images/Street/Tileset_6.png","collison":false},
  {"src":"../Images/Street/Tileset_15.png","collison":true},
  {"src":"../Images/Street/Tileset_15.png","collison":true},
  {"src":"../Images/Street/Tileset_15.png","collison":true},
  {"src":"../Images/Street/Tileset_15.png","collison":true},
  {"src":"../Images/Street/Tileset_15.png","collison":true},
  {"src":"../Images/Street/Tileset_15.png","collison":true},
  {"src":"../Images/Street/Tileset_15.png","collison":true},
  {"src":"../Images/Street/Tileset_15.png","collison":true},
  {"src":"../Images/Street/Tileset_5.png","collison":false},
  {"src":"../Images/Street/Tileset_6.png","collison":false},
  {"src":"../Images/Street/Tileset_15.png","collison":true},
  {"src":"../Images/Street/Tileset_15.png","collison":true},
  {"src":"../Images/Street/Tileset_15.png","collison":true},
  {"src":"../Images/Street/Tileset_15.png","collison":true},
  {"src":"../Images/Street/Tileset_15.png","collison":true},
  {"src":"../Images/Street/Tileset_15.png","collison":true},
  {"src":"../Images/Street/Tileset_15.png","collison":true},
  {"src":"../Images/Street/Tileset_15.png","collison":true},
  {"src":"../Images/Street/Tileset_5.png","collison":false},
  {"src":"../Images/Street/Tileset_6.png","collison":false},
  {"src":"../Images/Street/Tileset_15.png","collison":true},
  {"src":"../Images/Street/Tileset_15.png","collison":true},
  {"src":"../Images/Street/Tileset_15.png","collison":true},
  {"src":"../Images/Street/Tileset_15.png","collison":true}
]